{
  "graphs" : [
    {
      "metadata" : {
        "gress" : "ingress",
        "description" : "Before Table Placement Round 1",
        "placement_complete" : false
      },
      "nodes" : [
        {
          "id" : "0",
          "metadata" : {
            "tables" : [
              {
                "name" : "cond-2",
                "table_type" : "condition",
                "condition" : "hdr.ipv4.$valid == 1"
              }
            ],
            "min_stage" : 1,
            "dep_chain" : 0
          }
        },
        {
          "id" : "1",
          "metadata" : {
            "tables" : [
              {
                "name" : "Ingress.ipv4_lpm",
                "table_type" : "match",
                "match_type" : "ternary"
              }
            ],
            "min_stage" : 2,
            "dep_chain" : 0
          }
        },
        {
          "id" : "2",
          "metadata" : {
            "tables" : [
              {
                "name" : "Ingress.m_meter",
                "table_type" : "match",
                "match_type" : "exact"
              },
              {
                "name" : "Ingress.meter",
                "table_type" : "meter"
              }
            ],
            "min_stage" : 0,
            "dep_chain" : 2
          }
        },
        {
          "id" : "3",
          "metadata" : {
            "tables" : [
              {
                "name" : "Ingress.m_filter",
                "table_type" : "match",
                "match_type" : "exact"
              }
            ],
            "min_stage" : 1,
            "dep_chain" : 1
          }
        },
        {
          "id" : "4",
          "metadata" : {
            "tables" : [
              {
                "name" : "SINK",
                "table_type" : "condition",
                "condition" : "<null>"
              }
            ],
            "min_stage" : -1,
            "dep_chain" : -1
          }
        }
      ],
      "edges" : [
        {
          "id" : "0",
          "source" : "0",
          "target" : "1",
          "metadata" : {
            "type" : "control",
            "sub_type" : "condition",
            "condition_value" : true,
            "tags" : ["dependency"]
          }
        },
        {
          "id" : "1",
          "source" : "2",
          "target" : "3",
          "metadata" : {
            "type" : "match",
            "sub_type" : "ixbar_read",
            "dep_fields" : [
              {
                "gress" : "ingress",
                "field_name" : "meta.tmp_digest.meterTag",
                "start_bit" : 0,
                "width" : 8
              }
            ],
            "is_critical" : true,
            "tags" : ["dependency"]
          }
        },
        {
          "id" : "2",
          "source" : "3",
          "target" : "1",
          "metadata" : {
            "type" : "action",
            "sub_type" : "output",
            "dep_fields" : [
              {
                "gress" : "ingress",
                "field_name" : "ig_intr_md_for_dprsr.drop_ctl",
                "start_bit" : 0,
                "width" : 3
              }
            ],
            "is_critical" : true,
            "tags" : ["dependency"]
          }
        },
        {
          "id" : "3",
          "source" : "3",
          "target" : "0",
          "metadata" : {
            "type" : "control",
            "sub_type" : "anti",
            "anti_type" : "next_table_data",
            "dep_fields" : [
              {
                "gress" : "ingress",
                "field_name" : "ig_intr_md_for_dprsr.drop_ctl",
                "start_bit" : 0,
                "width" : 3
              }
            ],
            "is_critical" : true,
            "tags" : ["dependency"]
          }
        },
        {
          "id" : "4",
          "source" : "2",
          "target" : "3",
          "metadata" : {
            "type" : "control",
            "sub_type" : "anti",
            "anti_type" : "next_table_data",
            "dep_fields" : [
              {
                "gress" : "ingress",
                "field_name" : "meta.tmp_digest.meterTag",
                "start_bit" : 0,
                "width" : 8
              }
            ],
            "tags" : ["dependency"]
          }
        },
        {
          "id" : "5",
          "source" : "2",
          "target" : "3",
          "metadata" : {
            "type" : "control",
            "sub_type" : "default_next_table",
            "is_critical" : true,
            "tags" : ["flow"]
          }
        },
        {
          "id" : "6",
          "source" : "3",
          "target" : "0",
          "metadata" : {
            "type" : "control",
            "sub_type" : "default_next_table",
            "is_critical" : true,
            "tags" : ["flow"]
          }
        },
        {
          "id" : "7",
          "source" : "0",
          "target" : "1",
          "metadata" : {
            "type" : "control",
            "sub_type" : "condition",
            "condition_value" : true,
            "is_critical" : true,
            "tags" : ["flow"]
          }
        },
        {
          "id" : "8",
          "source" : "0",
          "target" : "4",
          "metadata" : {
            "type" : "control",
            "sub_type" : "condition",
            "condition_value" : false,
            "tags" : ["flow"]
          }
        },
        {
          "id" : "9",
          "source" : "1",
          "target" : "4",
          "metadata" : {
            "type" : "control",
            "sub_type" : "default_next_table",
            "tags" : ["flow"]
          }
        }
      ]
    },
    {
      "metadata" : {
        "gress" : "ingress",
        "description" : "After Table Placement Round 1",
        "placement_complete" : true
      },
      "nodes" : [
        {
          "id" : "0",
          "metadata" : {
            "placement" : {
              "logical_table_id" : 0,
              "stage_number" : 0
            },
            "tables" : [
              {
                "name" : "Ingress.m_meter",
                "table_type" : "match",
                "match_type" : "exact"
              },
              {
                "name" : "Ingress.meter",
                "table_type" : "meter"
              }
            ],
            "min_stage" : 0,
            "dep_chain" : 2
          }
        },
        {
          "id" : "1",
          "metadata" : {
            "placement" : {
              "logical_table_id" : 0,
              "stage_number" : 1
            },
            "tables" : [
              {
                "name" : "Ingress.m_filter",
                "table_type" : "match",
                "match_type" : "exact"
              }
            ],
            "min_stage" : 1,
            "dep_chain" : 1
          }
        },
        {
          "id" : "2",
          "metadata" : {
            "placement" : {
              "logical_table_id" : 0,
              "stage_number" : 2
            },
            "tables" : [
              {
                "name" : "Ingress.ipv4_lpm",
                "table_type" : "match",
                "match_type" : "ternary"
              },
              {
                "name" : "ipv4_lpm_0$tind",
                "table_type" : "ternary_indirect"
              },
              {
                "name" : "Ingress.ipv4_lpm$action",
                "table_type" : "action"
              }
            ],
            "min_stage" : 2,
            "dep_chain" : 0
          }
        },
        {
          "id" : "3",
          "metadata" : {
            "tables" : [
              {
                "name" : "SINK",
                "table_type" : "condition",
                "condition" : "<null>"
              }
            ],
            "min_stage" : -1,
            "dep_chain" : -1
          }
        }
      ],
      "edges" : [
        {
          "id" : "0",
          "source" : "0",
          "target" : "1",
          "metadata" : {
            "type" : "match",
            "sub_type" : "ixbar_read",
            "dep_fields" : [
              {
                "gress" : "ingress",
                "field_name" : "meta.tmp_digest.meterTag",
                "start_bit" : 0,
                "width" : 8
              }
            ],
            "is_critical" : true,
            "tags" : ["dependency"]
          }
        },
        {
          "id" : "1",
          "source" : "1",
          "target" : "2",
          "metadata" : {
            "type" : "action",
            "sub_type" : "output",
            "dep_fields" : [
              {
                "gress" : "ingress",
                "field_name" : "ig_intr_md_for_dprsr.drop_ctl",
                "start_bit" : 0,
                "width" : 3
              }
            ],
            "is_critical" : true,
            "tags" : ["dependency"]
          }
        },
        {
          "id" : "2",
          "source" : "1",
          "target" : "2",
          "metadata" : {
            "type" : "control",
            "sub_type" : "anti",
            "anti_type" : "next_table_data",
            "dep_fields" : [
              {
                "gress" : "ingress",
                "field_name" : "ig_intr_md_for_dprsr.drop_ctl",
                "start_bit" : 0,
                "width" : 3
              }
            ],
            "tags" : ["dependency"]
          }
        },
        {
          "id" : "3",
          "source" : "0",
          "target" : "1",
          "metadata" : {
            "type" : "control",
            "sub_type" : "anti",
            "anti_type" : "next_table_data",
            "dep_fields" : [
              {
                "gress" : "ingress",
                "field_name" : "meta.tmp_digest.meterTag",
                "start_bit" : 0,
                "width" : 8
              }
            ],
            "tags" : ["dependency"]
          }
        },
        {
          "id" : "4",
          "source" : "0",
          "target" : "1",
          "metadata" : {
            "type" : "control",
            "sub_type" : "default_next_table",
            "is_critical" : true,
            "tags" : ["flow"]
          }
        },
        {
          "id" : "5",
          "source" : "1",
          "target" : "2",
          "metadata" : {
            "type" : "control",
            "sub_type" : "default_next_table",
            "is_critical" : true,
            "tags" : ["flow"]
          }
        },
        {
          "id" : "6",
          "source" : "2",
          "target" : "3",
          "metadata" : {
            "type" : "control",
            "sub_type" : "condition",
            "condition_value" : false,
            "tags" : ["flow"]
          }
        }
      ]
    }
  ],
  "schema_version" : "1.0.1"
}